Gentoro/Gentoro.py
Gentoro/GentoroTypes.py
Gentoro/__init__.py
Gentoro-0.1.9.dist-info/LICENSE
Gentoro-0.1.9.dist-info/METADATA
Gentoro-0.1.9.dist-info/WHEEL
Gentoro-0.1.9.dist-info/top_level.txt
Gentoro-0.1.9.dist-info/RECORD
