Metadata-Version: 2.1
Name: Gentoro
Version: 0.1.9
Summary: Gentoro Python SDK for AI tool execution and authentication
Home-page: https://github.com/gentoro-GT/python-sdk
Author: Gentoro R&D
Author-email: communitysupport@gentoro.com
License: Apache-2.0
Classifier: Programming Language :: Python :: 3
Classifier: License :: OSI Approved :: Apache Software License
Classifier: Operating System :: OS Independent
Requires-Python: >=3.7
License-File: LICENSE
Requires-Dist: annotated-types==0.7.0
Requires-Dist: anyio==4.8.0
Requires-Dist: backports.tarfile==1.2.0
Requires-Dist: certifi==2025.1.31
Requires-Dist: charset-normalizer==3.4.1
Requires-Dist: colorama==0.4.6
Requires-Dist: distro==1.9.0
Requires-Dist: docutils==0.21.2
Requires-Dist: h11==0.14.0
Requires-Dist: httpcore==1.0.7
Requires-Dist: httpx==0.28.1
Requires-Dist: id==1.5.0
Requires-Dist: idna==3.10
Requires-Dist: importlib-metadata==8.6.1
Requires-Dist: jaraco.classes==3.4.0
Requires-Dist: jaraco.context==6.0.1
Requires-Dist: jaraco.functools==4.1.0
Requires-Dist: jiter==0.8.2
Requires-Dist: jsonpatch>=1.33
Requires-Dist: jsonpointer>=3.0.0
Requires-Dist: keyring==25.6.0
Requires-Dist: langchain-core>=0.3.49
Requires-Dist: langchain-openai>=0.3.11
Requires-Dist: langsmith>=0.3.19
Requires-Dist: markdown-it-py==3.0.0
Requires-Dist: mdurl==0.1.2
Requires-Dist: more-itertools==10.6.0
Requires-Dist: nh3==0.2.20
Requires-Dist: openai>=1.69.0
Requires-Dist: orjson==3.10.16
Requires-Dist: packaging==24.2
Requires-Dist: pydantic==2.10.6
Requires-Dist: pydantic-core==2.27.2
Requires-Dist: Pygments==2.19.1
Requires-Dist: python-dotenv==1.0.1
Requires-Dist: pywin32-ctypes==0.2.3
Requires-Dist: PyYAML>=6.0.2
Requires-Dist: readme-renderer==44.0
Requires-Dist: regex>=2024.11.6
Requires-Dist: requests>=2.32.3
Requires-Dist: requests-toolbelt>=1.0.0
Requires-Dist: rfc3986==2.0.0
Requires-Dist: rich==13.9.4
Requires-Dist: sniffio==1.3.1
Requires-Dist: tenacity>=9.0.0
Requires-Dist: tiktoken>=0.9.0
Requires-Dist: tqdm==4.67.1
Requires-Dist: twine==6.1.0
Requires-Dist: typing-extensions>=4.12.2
Requires-Dist: urllib3==2.3.0
Requires-Dist: zipp==3.21.0
Requires-Dist: zstandard>=0.23.0
